CHANGELOG.txt
LICENCE.txt
MANIFEST.in
README.txt
setup.py
pkss_form_validator/__init__.py
pkss_form_validator.egg-info/PKG-INFO
pkss_form_validator.egg-info/SOURCES.txt
pkss_form_validator.egg-info/dependency_links.txt
pkss_form_validator.egg-info/top_level.txt