Metadata-Version: 2.1
Name: pkss-form-validator
Version: 0.0.1
Summary: A Form Inputs Validator
Home-page: 
Author: Vinoth
Author-email: vinothmoorthy1397@gmail.com
License: MIT
Keywords: validator
Classifier: Development Status :: 5 - Production/Stable
Classifier: Intended Audience :: Education
Classifier: Operating System :: Microsoft :: Windows :: Windows 10
Classifier: License :: OSI Approved :: MIT License
Classifier: Programming Language :: Python :: 3
License-File: LICENCE.txt
